[{"Title":"Nginx 学习系列（二） ------------- 负载均衡","Id":"","OriginalUrl":"https://juejin.im/post/5b6a45d5f265da0f9402d118","CommentCount":4,"LikeCount":0},{"Title":"使用多线程查询百万条用户数据将汉字转化成拼音","Id":"","OriginalUrl":"https://juejin.im/post/5b839bd851882542f5047412","CommentCount":10,"LikeCount":0},{"Title":"Spring Boot中如何扩展XML请求和响应的支持","Id":"","OriginalUrl":"http://blog.didispace.com/spring-boot-xml-httpmessageconverter/","CommentCount":0,"LikeCount":0},{"Title":"还在用Synchronized？Atomic你了解不？","Id":"","OriginalUrl":"https://juejin.im/post/5bf6469ae51d45223f44d897","CommentCount":12,"LikeCount":0},{"Title":"微信小程序授权登陆方案以及在Taro下利用Decorator修饰器实现","Id":"","OriginalUrl":"https://juejin.im/post/5b97a762e51d450e9649a8fd","CommentCount":11,"LikeCount":0},{"Title":"Java开发必须掌握的线上问题排查命令","Id":"","OriginalUrl":"https://juejin.im/post/5ac442946fb9a028d700cfdf","CommentCount":2,"LikeCount":0},{"Title":"基于大中台架构的电商业务中台最佳实践之二：交易业务中台核心设计","Id":"","OriginalUrl":"https://juejin.im/post/5bd1edbae51d457a7e4f99ed","CommentCount":3,"LikeCount":0},{"Title":"App抓包其实没那么复杂！Charles来帮你搞定","Id":"","OriginalUrl":"https://juejin.im/post/5ad045d2f265da2385334555","CommentCount":5,"LikeCount":0},{"Title":"AOP如何实现及实现原理","Id":"","OriginalUrl":"https://juejin.im/post/5bf4fc84f265da611b57f906","CommentCount":0,"LikeCount":0},{"Title":"Vue单页及多页应用全局配置404页面实践","Id":"","OriginalUrl":"https://juejin.im/post/5b019ad7f265da0ba567d259","CommentCount":4,"LikeCount":0},{"Title":"频繁GC (Allocation Failure)及young gc时间过长分析","Id":"","OriginalUrl":"https://juejin.im/post/5a9b811a6fb9a028e46e1c88","CommentCount":0,"LikeCount":0},{"Title":"Spring统一返回Json工具类，带分页信息","Id":"","OriginalUrl":"https://juejin.im/post/5ae722546fb9a07aa83e8343","CommentCount":15,"LikeCount":0},{"Title":"《快学 Go 语言》第 8 课 —— 程序大厦是如何构建起来的","Id":"","OriginalUrl":"https://juejin.im/post/5bf76783e51d45599d422a2b","CommentCount":9,"LikeCount":0},{"Title":"《快学 Go 语言》第 12 课 —— 通道","Id":"","OriginalUrl":"https://juejin.im/post/5c0888cd6fb9a049c15f0170","CommentCount":2,"LikeCount":0},{"Title":"MySQL探索(一):B-Tree索引","Id":"","OriginalUrl":"https://juejin.im/post/5b5c2096f265da0f65239483","CommentCount":5,"LikeCount":0},{"Title":"看图轻松理解数据结构与算法系列(Trie树)","Id":"","OriginalUrl":"https://juejin.im/post/5ba198ba5188255c7c6555c9","CommentCount":3,"LikeCount":0},{"Title":"SpringBoot整合dubbo","Id":"","OriginalUrl":"https://juejin.im/post/5b21d6696fb9a01e4e5e6e63","CommentCount":11,"LikeCount":0},{"Title":"统治软件开发中的著名定律","Id":"","OriginalUrl":"http://mp.weixin.qq.com/s?__biz=MzAxOTc0NzExNg==\u0026mid=2665515835\u0026idx=2\u0026sn=b0d4f151316ec0c6753d7af7dc55f49a\u0026chksm=80d67378b7a1fa6ea136d67d2b065b4c6e8d822890eea53288031771f20e519c298663343f16#rd","CommentCount":0,"LikeCount":0},{"Title":"使用Google Guava快乐编程","Id":"","OriginalUrl":"https://juejin.im/post/5bbdb2cff265da0afb3364d6","CommentCount":0,"LikeCount":0},{"Title":"Web API 文档生成工具 apidoc","Id":"","OriginalUrl":"https://juejin.im/post/5a6684e3518825732646eef8","CommentCount":8,"LikeCount":0}]