{"ID":"cbdd83b0a8c6","Title":"临江仙·高咏楚词酬午日","Author":{"ID":0,"CreatedAt":"0001-01-01T00:00:00Z","UpdatedAt":"0001-01-01T00:00:00Z","DeletedAt":null,"Name":"陈与义 ","Profile":"","Picture":""},"Dynasty":"宋代","Content":"\n高咏楚词酬午日，天涯节序匆匆。榴花不似舞裙红。无人知此意，歌罢满帘风。 万事一身伤老矣，戎葵凝笑墙东。酒杯深浅去年同。试浇桥下水，今夕到湘中。\n","Translate":"译文　　我放声吟诵楚辞，来度过端午。此时我漂泊在天涯远地，是一个匆匆过客。异乡的石榴花再红，也比不上京师里的舞者裙衫飘飞，那般艳丽。没有人能理解我此时的心意，慷慨悲歌后，只有一身风动凉过。万事在如今，只是空有一身老病在。墙东的蜀葵，仿佛也在嘲笑我的凄凉。杯中之酒，看起来与往年相似，我将它浇到桥下的江水，让江水会带着流到湘江去。注释午日：端午，酬：过，派遣。节序：节令。“榴花”句：言舞裙比石榴更红。这是怀念昔时生平岁月之意。戎葵：即蜀葵，花开五色，似木槿。展开阅读全文∨","Like":"　　此词是陈与义在公元1129年（建炎三年）所作，这一年，陈与义流寓湖南、湖北一带；据《简斋先生年谱》记载：“建炎三年己酉春在岳阳，四月，差知郢州；五月，避贵仲正寇，入洞庭。六月，贵仲正降，复从华容还岳阳。”又《宋史。陈与义传》载：“及金人入汴，高宗南迁，遂避乱襄汉，转湖湘，踚岭桥。”这首《临江仙》所反映的是国家遭受兵乱时节，作者在端午节凭吊屈原，旧怀伤时，借此来抒发自己的爱国情怀。　　词一开头，一语惊人。“高咏楚词”，透露了在节日中的感伤必绪和壮阔，胸襟，屈原的高洁品格给词人以激励，他高昂地吟诵楚辞，深感流落天涯之苦，节序匆匆，自己却报国无志。陈与义在两湖间流离之际展开阅读全文∨","Background":"　　此词为作者流寓邵州（湖南邵阳）时作，时为建炎四年（1130年）。避乱天南，再逢佳节。追忆中州盛日，不免凄然以悲。“无人”两句，以淡笔写深心。“试浇桥下水，今夕到湘中”，尤觉思远意长，婉曲沉挚。","Url":"https://so.gushiwen.org/shiwenv_cbdd83b0a8c6.aspx"}