{"ID":"27d0dc6c1078","Title":"临江仙·倦客如今老矣","Author":{"ID":0,"CreatedAt":"0001-01-01T00:00:00Z","UpdatedAt":"0001-01-01T00:00:00Z","DeletedAt":null,"Name":"史达祖 ","Profile":"","Picture":""},"Dynasty":"宋代","Content":"\n倦客如今老矣，旧时不奈春何。几曾湖上不经过。看花南陌醉，驻马翠楼歌。 远眼愁随芳草，湘裙忆著春罗。枉教装得旧时多。向来箫鼓地，犹见柳婆娑。(箫鼓地 一作：歌舞地)\n","Translate":"译文倦客如今已老矣，而春天还像旧时一样，每年都如期来到人间。可是我的心情已与过去大不相同，只能发出无可奈何花落去的感叹了。回忆以前经常在西湖一带泛舟西湖，观景看花，饮酒听歌，几无虚日。云见芳草触动愁思，不免忆起着春罗湘裙的歌童舞女。现在的一些歌伎舞女，她们打扮得比旧时歌伎舞女更加娇艳。西湖边上的婀娜柳枝临风婆娑而舞，只能令人追忆当年之歌喉舞腰而已。注释临江仙：词牌名。双调，五十八字或六十字，皆用平韵。倦客：词人自指。南陌：游乐之地。翠楼：词中指妓馆歌楼。远眼愁随芳草，湘裙忆着春罗：云见芳展开阅读全文∨","Like":"　　上片首句“倦客如今老矣”。词人自称“倦客”，是由于经历了生活的挫折，对人世产生了厌倦情绪的缘故。“旧时可奈春何”，春天每年都如期而至，但词人的心情却不同于往年，感叹的意味很重。下文转入回忆。“几曾湖上不经过。看花南陌醉，驻马翠楼歌”说往年经常在西湖一带游赏观光，几无虚日。“看花南陌醉，驻马翠楼歌”是全词中最精采的语句。它用华丽的字面勾画出了一幅由色彩、声音和动态所组成的形象鲜明的生活图景，概括了词人过去那段看花赏景、饮酒听歌的繁华热闹的生活经历。　　写到下片，词人又把回忆的内容集中在歌妓之类的人物身上。“远眼愁随芳草，湘裙忆着春罗”两句，由牛希济《生查子》的“记得绿展开阅读全文∨","Background":"　　开禧二年（1206年），韩侂胄举兵北伐，并败兵而回，词人受到牵连，被免职，发配边疆。根据张镦在嘉泰元年（1201年）辛酉所作的《梅溪词序》推断，词人失势之时应该已近50岁。《临江仙·倦客如今老矣》当作于词人被罢免、失势之后。","Url":"https://so.gushiwen.org/shiwenv_27d0dc6c1078.aspx"}