{"ID":"d0cee49fd157","Title":"原州九日","Author":{"ID":0,"CreatedAt":"0001-01-01T00:00:00Z","UpdatedAt":"0001-01-01T00:00:00Z","DeletedAt":null,"Name":"赵时春 ","Profile":"赵时春（公元—五0九年至一五六七年）字景仁，号浚谷，平凉人。生于明武宗正德四年，卒年不详。著有《赵浚谷集》十六卷，与《平凉府志》，均《四库总目》并行于世。赵时春居华亭多年，著有《惠民渠记》、《复古南门记》、《朝那庙碑记》、《重修灵岩寺记》、《剡山半雾》、《仪山歌》、《夜归仪州》、《登古仪州西城》、《华亭道中》、《华亭雨雾》等诗歌。► 5篇诗文","Picture":"https://www.gushiwen.org/authorImg/zhaoshichun.jpg"},"Dynasty":"明代","Content":"\n秋声咽塞笳，边气肃霜华。九日登高处，群山入望赊。苍蒹仍碧水，绿酒对黄花。鸿鹄归何处，长天空落霞。\n","Translate":"","Like":"","Background":"","Url":"https://so.gushiwen.org/shiwenv_d0cee49fd157.aspx"}