{"ID":"d8fa88252169","Title":"泂酌","Author":{"ID":0,"CreatedAt":"0001-01-01T00:00:00Z","UpdatedAt":"0001-01-01T00:00:00Z","DeletedAt":null,"Name":"佚名 ","Profile":"","Picture":""},"Dynasty":"先秦","Content":"\n泂酌彼行潦，挹彼注兹，可以餴饎。岂弟君子，民之父母。\n泂酌彼行潦，挹彼注兹，可以濯罍。岂弟君子，民之攸归。\n泂酌彼行潦，挹彼注兹，可以濯溉。岂弟君子，民之攸塈。\n","Translate":"译文远舀路边积水潭，把这水缸都装满，可以蒸菜也蒸饭。君子品德真高尚，好比百姓父母般。远舀路边积水坑，舀来倒进我水缸，可把酒壶洗清爽。君子品德真高尚，百姓归附心向往。远舀路边积水洼，舀进水瓮抱回家，可以洗涤和抹擦。君子品德真高尚，百姓归附爱戴他。注释泂（jiǒng）：远。酌（zhuó）：古通“爵”，中国古代的一种酒器。行（háng）潦（lǎo）：路边的积水。挹（yì）：舀出。注：灌入。餴（fēn）：蒸。饎（chì）：旧训酒食，非。岂弟（kǎitì）：即“恺悌”，本义为和乐平易，恺者，大也展开阅读全文∨","Like":"","Background":"　　对《大雅·泂酌》这首诗的，历来有争议。根据诗意，这可能是一首在家族内部大型宴会上唱的雅歌，疑似与《大雅·公刘》同在一个宴会上，人们对公刘的颂歌。而程俊英《诗经译注》认为：“这是歌颂统治者能得民心的诗，具体指谁，史无确证。”","Url":"https://so.gushiwen.org/shiwenv_d8fa88252169.aspx"}