{"ID":"3f98751b9dfc","Title":"溪上遇雨二首","Author":{"ID":0,"CreatedAt":"0001-01-01T00:00:00Z","UpdatedAt":"0001-01-01T00:00:00Z","DeletedAt":null,"Name":"崔道融 ","Profile":"崔道融，江陵人。唐末诗人。以征辟为永嘉（今浙江省温州市）令。累官至右补阙。后避居于闽，因号“东瓯散人”。与司空图为诗友，人称江陵才子。工绝句。僖宗乾符二年（875年），于永嘉山斋集诗500首，辑为《申唐诗》3卷。另有《东浮集》9卷，当为入闽后所作。► 73篇诗文","Picture":"https://www.gushiwen.org/authorImg/cuidaorong.jpg"},"Dynasty":"唐代","Content":"\n回塘雨脚如缫丝，野禽不起沈鱼飞。耕蓑钓笠取未暇，秋田有望从淋漓。\n坐看黑云衔猛雨，喷洒前山此独晴。忽惊云雨在头上，却是山前晚照明。\n","Translate":"译文环曲的池塘水面，雨水像在抽丝一般密织，野禽因为雨势太大无法起飞，鱼儿却惊得在水面飞跃起来。耕种的人和垂钓者都来不及取蓑衣和斗笠，秋季的田地都多么期待这么一场酣畅淋漓的大雨啊。我坐看天空中浓密的乌云含着雨水喷洒在前方的山峦上，而这里却依然阳光灿烂。忽然滚滚的乌云挟带着骤雨，已泻到了我的头上！不过我却意外地发现：前方青翠的山峰上，还映照着一抹夕阳的余晖！注释回塘：回曲的水池。南朝梁简文帝《入溆浦诗》：“泛水入回塘，空枝度日光。”唐杜甫《茅屋为秋风所破歌》：“床头屋漏无乾处，雨脚如麻未断绝。”缲（sāo）展开阅读全文∨","Like":"","Background":"","Url":"https://so.gushiwen.org/shiwenv_3f98751b9dfc.aspx"}