{"ID":"b7d5bf78c435","Title":"王元章倒枝梅画","Author":{"ID":0,"CreatedAt":"0001-01-01T00:00:00Z","UpdatedAt":"0001-01-01T00:00:00Z","DeletedAt":null,"Name":"徐渭 ","Profile":"徐渭（1521—1593），汉族，绍兴府山阴（今浙江绍兴）人。初字文清，后改字文长，号天池山人，或署田水月、田丹水，青藤老人、青藤道人、青藤居士、天池渔隐、金垒、金回山人、山阴布衣、白鹇山人、鹅鼻山侬等别号。中国明代文学家、书画家、军事家。民间也普遍流传他的故事传说，关于他年轻时如何聪明，后来如何捉弄官宦等。► 1545篇诗文","Picture":"https://www.gushiwen.org/authorImg/xuwei.jpg"},"Dynasty":"明代","Content":"\n皓态孤芳压俗姿，不堪复写拂云枝。从来万事嫌高格，莫怪梅花着地垂。\n","Translate":"","Like":"　　“皓态孤芳压俗姿，不堪复写拂云枝。从来万事兼高格，莫怪梅花着地垂。”这是一首题画诗，是徐渭题咏王冕《倒枝梅画》的。　　王元章即王冕，他是元末明初诗人、画家，字元章，号竹斋，别号梅花屋主，浙江诸暨人。徐渭和王冕在经历和个性上有些共同点。王冕主要生活在元代，屡应进士试，都不中。也不屑做州县小官，只临死那年，朱元璋授以咨议参军之职。王冕的性格卓荦不群。徐渭生活在明代，也是屡试不中，终身不得志功名。只做过幕客，没有官职。徐渭生性放纵，不愿受传统礼法的束缚。他和王冕都喜欢游历，都会书画诗文。可能正是两人的这些共同点，使徐渭看到王冕的《倒枝梅画》有了写这首题画诗的灵感。诗通过评展开阅读全文∨","Background":"","Url":"https://so.gushiwen.org/shiwenv_b7d5bf78c435.aspx"}