{"ID":"ca10eb0f4c7f","Title":"见二十弟倡和花字漫兴五首·其一","Author":{"ID":0,"CreatedAt":"0001-01-01T00:00:00Z","UpdatedAt":"0001-01-01T00:00:00Z","DeletedAt":null,"Name":"黄庭坚 ","Profile":"黄庭坚（1045.8.9-1105.5.24），字鲁直，号山谷道人，晚号涪翁，洪州分宁（今江西省九江市修水县）人，北宋著名文学家、书法家，为盛极一时的江西诗派开山之祖，与杜甫、陈师道和陈与义素有“一祖三宗”（黄庭坚为其中一宗）之称。与张耒、晁补之、秦观都游学于苏轼门下，合称为“苏门四学士”。生前与苏轼齐名，世称“苏黄”。著有《山谷词》，且黄庭坚书法亦能独树一格，为“宋四家”之一。► 2644篇诗文","Picture":"https://www.gushiwen.org/authorImg/huangtingjian.jpg"},"Dynasty":"宋代","Content":"\n落絮游丝三月候，风吹雨洗一城花。未知东郭清明酒，何似西窗谷雨茶。\n","Translate":"译文柳絮纷飞，蛛丝游动，正值暮春三月，风吹雨洗满城落花。不知道在东城外共饮清明酒，比起坐在西窗下面共饮谷雨茶怎么样。注释未知：不知道。","Like":"","Background":"","Url":"https://so.gushiwen.org/shiwenv_ca10eb0f4c7f.aspx"}